src/__init__.py
src/calculators/__init__.py
src/calculators/base_calculator.py
src/calculators/nsw_calculator.py
src/calculators/wa_calculator.py
mdc_lsl-0.0.1.dist-info/METADATA
mdc_lsl-0.0.1.dist-info/WHEEL
mdc_lsl-0.0.1.dist-info/RECORD
