Metadata-Version: 2.3
Name: mdc-lsl
Version: 0.0.1
Summary: LSL business rules logic for Melbourne Data Co
License: Commercial License Agreement
Author: Mick
Author-email: mick@melbournedata.co
Requires-Python: >=3.11,<4.0
Classifier: License :: Other/Proprietary License
Classifier: Programming Language :: Python :: 3
Classifier: Programming Language :: Python :: 3.11
Classifier: Programming Language :: Python :: 3.12
Classifier: Programming Language :: Python :: 3.13
Requires-Dist: python-dateutil (>=2.9.0.post0,<3.0.0)
